odoo/addons/account_move_line_sale_info/README.rst
odoo/addons/account_move_line_sale_info/__init__.py
odoo/addons/account_move_line_sale_info/__manifest__.py
odoo/addons/account_move_line_sale_info/hooks.py
odoo/addons/account_move_line_sale_info/i18n/account_move_line_sale_info.pot
odoo/addons/account_move_line_sale_info/migrations/13.0.1.0.0/pre-migration.py
odoo/addons/account_move_line_sale_info/models/__init__.py
odoo/addons/account_move_line_sale_info/models/account_move.py
odoo/addons/account_move_line_sale_info/models/sale_order_line.py
odoo/addons/account_move_line_sale_info/models/stock_move.py
odoo/addons/account_move_line_sale_info/security/account_security.xml
odoo/addons/account_move_line_sale_info/static/description/icon.png
odoo/addons/account_move_line_sale_info/tests/__init__.py
odoo/addons/account_move_line_sale_info/tests/test_account_move_line_sale_info.py
odoo/addons/account_move_line_sale_info/views/account_move_view.xml
odoo13_addon_account_move_line_sale_info-13.0.1.0.5.dist-info/METADATA
odoo13_addon_account_move_line_sale_info-13.0.1.0.5.dist-info/WHEEL
odoo13_addon_account_move_line_sale_info-13.0.1.0.5.dist-info/top_level.txt
odoo13_addon_account_move_line_sale_info-13.0.1.0.5.dist-info/RECORD
