Metadata-Version: 2.1
Name: odoo13-addon-account-move-line-sale-info
Version: 13.0.1.0.5
Summary: Introduces the purchase order line to the journal items
Home-page: https://github.com/OCA/account-financial-tools
Author: ForgeFlow S.L., Odoo Community Association (OCA)
Author-email: support@odoo-community.org
License: AGPL-3
Platform: UNKNOWN
Classifier: Programming Language :: Python
Classifier: Framework :: Odoo
Classifier: Framework :: Odoo :: 13.0
Classifier: License :: OSI Approved :: GNU Affero General Public License v3
Requires-Python: >=3.5
Requires-Dist: odoo13-addon-account-move-line-stock-info
Requires-Dist: odoo13-addon-stock-account-prepare-anglo-saxon-out-lines-hook
Requires-Dist: odoo (<13.1dev,>=13.0a)
